setup.py
jiangwei_test/__init__.py
jiangwei_test/main.py
jiangwei_test.egg-info/PKG-INFO
jiangwei_test.egg-info/SOURCES.txt
jiangwei_test.egg-info/dependency_links.txt
jiangwei_test.egg-info/entry_points.txt
jiangwei_test.egg-info/not-zip-safe
jiangwei_test.egg-info/requires.txt
jiangwei_test.egg-info/top_level.txt