Metadata-Version: 1.0
Name: jiangwei-test
Version: 0.20
Summary: a console translation dictionary used dict.baidu.com Api
Home-page: http://www.xjiangwei.cn
Author: 蒋为
Author-email: ok@xjiangwei.cn
License: UNKNOWN
Keywords: python english translation dictionary terminal
Platform: UNKNOWN
